MANIFEST.in
README.rst
setup.py
docs/HISTORY.txt
docs/INSTALL.txt
docs/LICENSE.GPL
docs/LICENSE.txt
monet/__init__.py
monet.calendar.criteria.egg-info/PKG-INFO
monet.calendar.criteria.egg-info/SOURCES.txt
monet.calendar.criteria.egg-info/dependency_links.txt
monet.calendar.criteria.egg-info/entry_points.txt
monet.calendar.criteria.egg-info/namespace_packages.txt
monet.calendar.criteria.egg-info/not-zip-safe
monet.calendar.criteria.egg-info/requires.txt
monet.calendar.criteria.egg-info/top_level.txt
monet/calendar/__init__.py
monet/calendar/criteria/__init__.py
monet/calendar/criteria/config.py
monet/calendar/criteria/configure.zcml
monet/calendar/criteria/duration_event_criteria.py
monet/calendar/criteria/i18n.sh
monet/calendar/criteria/setuphandler.py
monet/calendar/criteria/tests.py
monet/calendar/criteria/i18n/plone-monet.calendar.criteria.po
monet/calendar/criteria/i18n/plone-monet.calendar.criteria.pot
monet/calendar/criteria/profiles/default/metadata.xml
monet/calendar/criteria/profiles/default/portal_atct.xml