Metadata-Version: 1.0
Name: monet.calendar.criteria
Version: 0.2.0
Summary: Additional Plone collection criteria for Monet Calendar suite
Home-page: http://plone.org/products/monet.calendar.star
Author: RedTurtle Technology
Author-email: sviluppoplone@redturtle.it
License: GPL
Keywords: plone plonegov calendar event collection
Platform: UNKNOWN
Classifier: Framework :: Plone
Classifier: Framework :: Plone :: 4.2
Classifier: Framework :: Plone :: 4.3
Classifier: Programming Language :: Python
